DeepPeak/.DS_Store
DeepPeak/__init__.py
DeepPeak/_version.py
DeepPeak/dataset.py
DeepPeak/directories.py
DeepPeak/helper.py
DeepPeak/kernel.py
DeepPeak/signals.py
DeepPeak/utils.py
DeepPeak/visualization.py
DeepPeak/algorithms/__init__.py
DeepPeak/algorithms/base.py
DeepPeak/algorithms/cholesky_solver.py
DeepPeak/algorithms/closed_form_solver.py
DeepPeak/algorithms/non_maximum_suppression copy.py
DeepPeak/algorithms/non_maximum_suppression.py
DeepPeak/algorithms/zero_crossing.py
DeepPeak/machine_learning/__init__.py
DeepPeak/machine_learning/classifier/__init__.py
DeepPeak/machine_learning/classifier/autoencoder.py
DeepPeak/machine_learning/classifier/base.py
DeepPeak/machine_learning/classifier/dense.py
DeepPeak/machine_learning/classifier/metrics.py
DeepPeak/machine_learning/classifier/utils.py
DeepPeak/machine_learning/classifier/wavenet.py
DeepPeak/machine_learning/weights/ROI_128.keras
DeepPeak/machine_learning/weights/__init__.py
DeepPeak/machine_learning/weights/temporary.keras
deeppeak-0.0.7.dist-info/licenses/LICENSE
deeppeak-0.0.7.dist-info/METADATA
deeppeak-0.0.7.dist-info/WHEEL
deeppeak-0.0.7.dist-info/top_level.txt
deeppeak-0.0.7.dist-info/RECORD
