Metadata-Version: 2.4
Name: DeepPeak
Version: 0.0.7
Summary: A package for deep-learning peak detection.
Author-email: Martin Poinsinet de Sivry-Houle <martin.poinsinet.de.sivry@gmail.com>
License: MIT License
Project-URL: Homepage, https://github.com/MartinPdeS/DeepPeak
Project-URL: Documentation, https://martinpdes.github.io/DeepPeak/
Project-URL: Repository, https://github.com/MartinPdeS/DeepPeak.git
Keywords: refracive index,optics,microbeads,Mie scattering
Classifier: Programming Language :: Python
Classifier: Programming Language :: Python :: 3
Classifier: Programming Language :: Python :: Implementation :: CPython
Classifier: Development Status :: 3 - Alpha
Classifier: Topic :: Scientific/Engineering :: Physics
Classifier: License :: OSI Approved :: MIT License
Classifier: Intended Audience :: Science/Research
Requires-Python: >=3.10
License-File: LICENSE
Requires-Dist: numpy
Requires-Dist: tensorflow
Requires-Dist: scikit-learn
Requires-Dist: MPSPlots
Provides-Extra: testing
Requires-Dist: pytest>=0.6; extra == "testing"
Requires-Dist: pytest-cov>=2.0; extra == "testing"
Requires-Dist: pytest-json-report==1.5.0; extra == "testing"
Requires-Dist: coverage==7.10.7; extra == "testing"
Provides-Extra: documentation
Requires-Dist: numpydoc==1.9.0; extra == "documentation"
Requires-Dist: sphinx>=5.1.1; extra == "documentation"
Requires-Dist: sphinx-rtd-theme==3.0.2; extra == "documentation"
Requires-Dist: sphinx-gallery==0.19.0; extra == "documentation"
Requires-Dist: pydata-sphinx-theme==0.16.1; extra == "documentation"
Provides-Extra: dev
Requires-Dist: flake8==7.3.0; extra == "dev"
Dynamic: license-file
